{
  "Actor": {
    "types": ["character", "npc"],

    "character": {
      "details": {
        "biography": "",
        "notes": ""
      },
      "reserves": {
        "power": {
          "value": 0,
          "max": 5,
          "strain": {
            "s1": false,
            "s2": false,
            "s3": false,
            "s4": false,
            "s5": false
          }
        },
        "grace": {
          "value": 0,
          "max": 5,
          "strain": {
            "s1": false,
            "s2": false,
            "s3": false,
            "s4": false,
            "s5": false
          }
        },
        "will": {
          "value": 0,
          "max": 5,
          "strain": {
            "s1": false,
            "s2": false,
            "s3": false,
            "s4": false,
            "s5": false
          }
        }
      },
      "tension": {
        "min": 0,
        "value": 0
      }
    },

    "npc": {
      "details": {
        "biography": "",
        "notes": ""
      },
      "health": {
        "hp": {
          "min": 0,
          "value": 4,
          "max": 4
        },
        "wounds": {
          "min": 0,
          "value": 1,
          "max": 1
      }
    }
  },

  "Item": {
    "types": [],
    "templates": {}
  }
}
